{
    "data": {
        "wiki": [
            {
                "url": "https://ja.wikipedia.org/?curid=2339154",
                "title": "SDコマンドガンダム G-ARMS オペレーションガンダム",
                "text": "〇〇は、1991年5月18日に発売されたバンダイ（後のバンダイナムコゲームス）のゲームボーイ用ソフト。"
            },
            {
                "url": "https://ja.wikipedia.org/?curid=487187",
                "title": "ハーバーサイド・クリスマス",
                "text": "〇〇は、2002年から2009年のクリスマスシーズンに東京ディズニーシー (TDS) で毎年行われていたスペシャルイベントの総称である。"
            },
            {
                "url": "https://ja.wikipedia.org/?curid=778701",
                "title": "カンタベリーピルグリム",
                "text": "〇〇は、イギリスの競走馬、繁殖牝馬である。イギリスオークスに優勝するなどのほか、繁殖牝馬としてチョーサーやスウィンフォードを送り出した。2歳下の半弟にダービー馬ジェッダがいる。"
            },
            {
                "url": "https://ja.wikipedia.org/?curid=3250147",
                "title": "天津租界",
                "text": "〇〇は、1860年から1947年のあいだ、イギリス、フランス、ドイツ、日本、アメリカ、イタリア、ロシア、オーストリア＝ハンガリーとベルギーなどの国が不平等条約や協定を通じて中国の天津旧市街の南東部に行政自治権と治外法権を設定した租借地である。"
            },
            {
                "url": "https://ja.wikipedia.org/?curid=348709",
                "title": "札幌市交通局8520形電車",
                "text": "〇〇は、札幌市交通局が1988年に導入した札幌市電の路面電車車両である。"
            }
        ]
    }
}