{
    "data": {
        "wiki": [
            {
                "url": "https://ja.wikipedia.org/?curid=1083691",
                "title": "電子制御ブレーキシステム",
                "text": "〇〇は、一般に電子制御制動力配分システム（でんしせいぎょせいどうりょくはいぶんシステム、Electronic Brake force Distribution、略称 EBD）とよばれる部分を指している。基本的にはアンチロックブレーキシステム（Antilock Brake System、略称 ABS）に付加されるもので、ブレーキを踏むと 前後輪の回転数や旋回状態から、制動力を車輪に対して最適に制御配分する。"
            },
            {
                "url": "https://ja.wikipedia.org/?curid=601820",
                "title": "ナッサウ家",
                "text": "〇〇は、ドイツ西部のライン地方を発祥としたヨーロッパの貴族、君主の家系。1代限りながら神聖ローマ帝国の君主（ローマ王）も出した家系で、現在のオランダ王家であるオラニエ＝〇〇、ルクセンブルク大公家であるナッサウ＝ヴァイルブルク家はともに同家の流れをくんでいる。"
            },
            {
                "url": "https://ja.wikipedia.org/?curid=3857595",
                "title": "乙黒圭祐",
                "text": "〇〇は、日本の男子レスリング（フリースタイル）選手。山梨県出身。身長176cm、リーチ182cm。山梨学院大学卒業。自衛隊体育学校所属の自衛官（2021年8月現在の階級は3等陸尉）。2020年東京オリンピック（2021年開催）のフリースタイル74kg級に出場。弟は同じ自衛隊体育学校に所属し、同オリンピックのフリースタイル65kg級金メダリストの乙黒拓斗。"
            },
            {
                "url": "https://ja.wikipedia.org/?curid=147963",
                "title": "国道347号",
                "text": "〇〇は、山形県寒河江市から宮城県大崎市に至る一般国道である。"
            },
            {
                "url": "https://ja.wikipedia.org/?curid=3056961",
                "title": "トーンモバイル",
                "text": "〇〇は、ドリーム・トレイン・インターネット（DTI）が仮想移動体通信事業者（MVNO）として提供する通信サービスである。"
            }
        ]
    }
}