{
    "data": {
        "wiki": [
            {
                "url": "https://ja.wikipedia.org/?curid=550447",
                "title": "ニキ・ド・サンファル",
                "text": "〇〇は、フランスの画家、彫刻家、造形作家、映像作家。本名カトリーヌ・マリー＝アニエス・ファル・ド・サン・ファル（Catherine Marie-Agnès Fal de Saint Phalle）。ファッション・モデルとして活躍した後、アートセラピーとして絵を描き始め、芸術表現による自己解放として射撃絵画を制作。挑発的・攻撃的な作品、特に社会における女性の役割を批判的に表現する作品（主にアサンブラージュ）から、やがて、女性性を肯定・強調する《ナナ》シリーズへと転じた。ストックホルム近代美術館の企画として制作した巨大なナナ像の《ホン》が大きな成功を収めて以来、《ナナ》やモンスター、神話・伝説に基づく鳥、蛇などをモチーフにした大規模な彫刻作品《ゴーレム》、《ノアの方舟》、《ストラヴィ"
            },
            {
                "url": "https://ja.wikipedia.org/?curid=3955632",
                "title": "藤井弘志",
                "text": "〇〇は、日本の農学者。農学博士（岩手大学）。山形大学農学部教授。酒田市長政策参与。"
            },
            {
                "url": "https://ja.wikipedia.org/?curid=259439",
                "title": "福井県道31号篠尾勝山線",
                "text": "〇〇は、福井県福井市と勝山市を結ぶ県道（主要地方道）である。"
            },
            {
                "url": "https://ja.wikipedia.org/?curid=1107930",
                "title": "キングフィッシュ (潜水艦)",
                "text": "〇〇は、アメリカ海軍の潜水艦。ガトー級潜水艦の一隻。艦名は大西洋西岸ではニベ科、中部太平洋ではサバ科、南太平洋ではアジ科など、各地で様々な魚の通俗名として使用されるキングフィッシュに因む。"
            },
            {
                "url": "https://ja.wikipedia.org/?curid=2808768",
                "title": "安藝正俊",
                "text": "〇〇は、東京都小金井市出身のサッカー選手。九州サッカーリーグ・沖縄SV所属。ポジションは、ディフェンダー。"
            }
        ]
    }
}