{
    "data": {
        "wiki": [
            {
                "url": "https://ja.wikipedia.org/?curid=986651",
                "title": "伊達村詮",
                "text": "〇〇は、江戸時代中期の陸奥国仙台藩一門第九席・川崎伊達家初代当主。"
            },
            {
                "url": "https://ja.wikipedia.org/?curid=4241780",
                "title": "恋するジェネレーション",
                "text": "〇〇は、2015年4月27日から2015年6月16日までKBS 2TVで放送された大韓民国のテレビドラマである。学校シリーズの6作目。主演はキム・ソヒョン、ユク・ソンジェ（BTOB）、ナム・ジュヒョク。"
            },
            {
                "url": "https://ja.wikipedia.org/?curid=1595094",
                "title": "旭町 (札幌市)",
                "text": "〇〇は、北海道札幌市豊平区の地名。現行行政地名は旭町1丁目から旭町7丁目。過去に厚別区(分区前は白石区)に存在した厚別町旭町とは異なる。"
            },
            {
                "url": "https://ja.wikipedia.org/?curid=669635",
                "title": "大野バスセンター",
                "text": "〇〇は、岐阜県揖斐郡大野町大字大野の大野町役場前にあるバス発着場である。北緯35.470333度 東経136.626755度﻿ / 35.470333; 136.626755"
            },
            {
                "url": "https://ja.wikipedia.org/?curid=2543664",
                "title": "オホーツクはまなす農業協同組合",
                "text": "〇〇は、北海道紋別市に拠点を置く農業協同組合である。略称はJAオホーツクはまなす。"
            }
        ]
    }
}