{
    "data": {
        "wiki": [
            {
                "url": "https://ja.wikipedia.org/?curid=3897820",
                "title": "安平拓馬",
                "text": "〇〇は、富山県氷見市出身のハンドボール選手。日本ハンドボールリーグの大崎電気所属。"
            },
            {
                "url": "https://ja.wikipedia.org/?curid=1808047",
                "title": "木村次郎右衛門",
                "text": "〇〇は、日本のスーパーセンテナリアン、ギネス世界記録保持者。京都府京丹後市に在住していた長寿の男性。2012年（平成24年）12月17日より死去するまで存命人物のうち世界最高齢者であった。また、同年12月28日にはクリスチャン・モーテンセンの115歳252日の記録を抜いて、死去した人物も含めた年齢が検証済みの歴代最高齢記録の男性となった。死去した時点での年齢は116歳54日（42422日）で、男性では歴代最高齢記録となっている。同い年の著名人に加藤シヅエ、パウロ6世、大佛次郎、有賀幸作、藤山愛一郎、李垠などがおり、彼が生まれた時点では後藤象二郎、陸奥宗光らが存命中であった。"
            },
            {
                "url": "https://ja.wikipedia.org/?curid=290297",
                "title": "アクセス権 (知る権利)",
                "text": "〇〇は、マスメディアに対して個人が意見発表の場を提供することを求める権利をいう。反論記事の掲載要求（反論権）や紙面・番組への参加などがこれにあたる。表現の自由の延長線上としてとらえられる比較的新しい概念である。アクセス権、すなわち\"right of access\"の本来の意味は「入手・利用する権利」であり、これは非常に広汎に用いられる言葉である。そのため多義に解される用語であるが、日本において多く語られるのはマスメディアへのアクセス権である。本項ではこれについて扱う。情報開示請求権を指してアクセス権と呼ぶ場合もある。これについては知る権利を参照。"
            },
            {
                "url": "https://ja.wikipedia.org/?curid=1039277",
                "title": "モンルージュ",
                "text": "〇〇は、長期の減少と横ばいののち、近年は増加に転じ、2003年の補完的国勢調査によると、42,002 人と見積もられている。市内にはパリメトロ4号線の終点メリー・ド・〇〇駅（〇〇市庁舎駅）と、パリメトロ13号線の終点シャティヨン＝〇〇駅がある。市の中心へのアクセスにはメリー・ド・〇〇駅のほうが便利である。クレディ・アグリコルの本社機能が〇〇に置かれている。"
            },
            {
                "url": "https://ja.wikipedia.org/?curid=694273",
                "title": "和歌山県立有田中央高等学校",
                "text": "〇〇は、和歌山県有田郡有田川町にある公立の高等学校である。"
            }
        ]
    }
}