{
    "data": {
        "wiki": [
            {
                "url": "https://ja.wikipedia.org/?curid=4176830",
                "title": "鄭鎬均",
                "text": "〇〇は、朝鮮民主主義人民共和国の軍人、政治家。朝鮮労働党中央委員会委員、朝鮮人民軍砲兵司令官などを歴任。朝鮮人民軍における軍事称号（階級）は大将。"
            },
            {
                "url": "https://ja.wikipedia.org/?curid=2409406",
                "title": "シャストリー・ナガー駅",
                "text": "〇〇は、インドデリーにあるデリー・メトロレッドラインの駅である。"
            },
            {
                "url": "https://ja.wikipedia.org/?curid=1930325",
                "title": "アデリナ・ソトニコワ",
                "text": "〇〇は、ロシアの元フィギュアスケート選手（女子シングル）。2014年ソチオリンピック金メダリスト。2011年世界ジュニア選手権優勝。ロシアフィギュアスケート選手権優勝4回。"
            },
            {
                "url": "https://ja.wikipedia.org/?curid=3595648",
                "title": "かんのん浜ポットホール",
                "text": "〇〇は、静岡県伊東市の城ヶ崎海岸に存在する甌穴（ポットホール）。甌穴内に球体の岩が残存する海蝕甌穴である。伊東市指定天然記念物。"
            },
            {
                "url": "https://ja.wikipedia.org/?curid=863798",
                "title": "夏のわかれ",
                "text": "〇〇は、東海テレビ制作のフジテレビ系列で、1968年7月1日～8月30日に放送された昼ドラマである。"
            }
        ]
    }
}