{
    "data": {
        "wiki": [
            {
                "url": "https://ja.wikipedia.org/?curid=2589829",
                "title": "日高山岳ビラパーク",
                "text": "〇〇は、北海道沙流郡日高町字富岡にある公園である。"
            },
            {
                "url": "https://ja.wikipedia.org/?curid=664218",
                "title": "宇多野ユースホステル",
                "text": "〇〇は、京都府京都市右京区にある公営（京都市営）のユースホステル。改修工事のため2006年8月31日をもって休館し、建替えをへて2008年7月12日より営業再開した。定員170名。正式名称は京都市〇〇。指定管理者制度により一般財団法人京都ユースホステル協会が管理運営を行っている。"
            },
            {
                "url": "https://ja.wikipedia.org/?curid=3982812",
                "title": "SUNRISE BEYOND",
                "text": "〇〇は、日本のアニメ制作会社。株式会社サンライズの子会社。"
            },
            {
                "url": "https://ja.wikipedia.org/?curid=2574602",
                "title": "長久手歴史トラベラーズ",
                "text": "〇〇は、愛知県長久手市で活動する観光PRユニットである。愛称は長トラ。"
            },
            {
                "url": "https://ja.wikipedia.org/?curid=3859702",
                "title": "Bamboo Flute Orchestra",
                "text": "〇〇は、女性尺八奏者5人組の音楽グループ。"
            }
        ]
    }
}