{
    "data": {
        "wiki": [
            {
                "url": "https://ja.wikipedia.org/?curid=2180612",
                "title": "ギブアップ嬢",
                "text": "〇〇は、日本テレビ系列で2010年10月12日から2011年3月29日まで毎週火曜日の23:58 - 翌0:29（JST、特別編成等で遅延の場合もあり）に放送されたトークバラエティ番組である。ハイビジョン制作。2010年4月10日に放送されたパイロット版『女芸人軍団の××な質問に30分答え続けたら100万円!ギブアップ・トーク!』が好評だったことからレギュラー化された。"
            },
            {
                "url": "https://ja.wikipedia.org/?curid=931640",
                "title": "BEST COLLECTION (オフコースのアルバム)",
                "text": "〇〇は、1985年8月31日に発売されたオフコース通算4作目のベスト・アルバム。"
            },
            {
                "url": "https://ja.wikipedia.org/?curid=1290410",
                "title": "ホンダ・CR-Z",
                "text": "〇〇は、本田技研工業が生産・販売していたハイブリッドエンジンを搭載したコンパクトクーペスポーツカーである。"
            },
            {
                "url": "https://ja.wikipedia.org/?curid=1313124",
                "title": "トロナジャパン",
                "text": "〇〇は、ゼンショーグループの食品メーカー。ピザおよびピザ関連商品を専門に扱う。なかでもクラスト（ピザ生地）は50%前後のシェアを有する。この他、ゼンショーグループの一般向け通信販売も担当している。"
            },
            {
                "url": "https://ja.wikipedia.org/?curid=3985009",
                "title": "501LV",
                "text": "〇〇は、Lenovoが製造販売したタブレット。ソフトバンク、Y!mobileで取り扱われていた。"
            }
        ]
    }
}